pyfilebrowser/__init__.py
pyfilebrowser/main.py
pyfilebrowser/requirements.txt
pyfilebrowser/modals/config.py
pyfilebrowser/modals/models.py
pyfilebrowser/modals/settings.py
pyfilebrowser/modals/users.py
pyfilebrowser/proxy/__init__.py
pyfilebrowser/proxy/database.py
pyfilebrowser/proxy/main.py
pyfilebrowser/proxy/rate_limit.py
pyfilebrowser/proxy/repeated_timer.py
pyfilebrowser/proxy/server.py
pyfilebrowser/proxy/settings.py
pyfilebrowser/proxy/squire.py
pyfilebrowser/proxy/templates/__init__.py
pyfilebrowser/proxy/templates/error.html
pyfilebrowser/proxy/templates/templates.py
pyfilebrowser/proxy/templates/warn.html
pyfilebrowser/squire/download.py
pyfilebrowser/squire/steward.py
pyfilebrowser/squire/struct.py
pyfilebrowser-0.2.0.dist-info/licenses/LICENSE
pyfilebrowser-0.2.0.dist-info/METADATA
pyfilebrowser-0.2.0.dist-info/WHEEL
pyfilebrowser-0.2.0.dist-info/entry_points.txt
pyfilebrowser-0.2.0.dist-info/top_level.txt
pyfilebrowser-0.2.0.dist-info/RECORD
