Metadata-Version: 2.4
Name: pyfilebrowser
Version: 0.2.0
Summary: Python module designed to streamline interactions with filebrowser
Author-email: Vignesh Rao <svignesh1793@gmail.com>
License: MIT License
Project-URL: Homepage, https://github.com/thevickypedia/pyfilebrowser
Project-URL: Docs, https://thevickypedia.github.io/pyfilebrowser/
Project-URL: Source, https://github.com/thevickypedia/pyfilebrowser
Project-URL: Bug Tracker, https://github.com/thevickypedia/pyfilebrowser/issues
Project-URL: Release Notes, https://github.com/thevickypedia/pyfilebrowser/blob/main/release_notes.rst
Keywords: filebrowser,pydantic,python-dotenv
Classifier: Development Status :: 5 - Production/Stable
Classifier: Intended Audience :: Information Technology
Classifier: License :: OSI Approved :: MIT License
Classifier: Operating System :: OS Independent
Classifier: Programming Language :: Python :: 3.11
Classifier: Programming Language :: Python :: 3.12
Classifier: Topic :: Communications :: File Sharing
Requires-Python: >=3.11
License-File: LICENSE
Requires-Dist: bcrypt==4.1.*
Requires-Dist: fastapi==0.111.*
Requires-Dist: httpx==0.27.*
Requires-Dist: Jinja2==3.1.*
Requires-Dist: pydantic==2.7.*
Requires-Dist: pydantic-settings==2.3.*
Requires-Dist: PyYaml==6.0.*
Requires-Dist: requests==2.32.*
Requires-Dist: user-agents==2.2.*
Requires-Dist: uvicorn==0.30.*
Provides-Extra: dev
Requires-Dist: sphinx==5.1.1; extra == "dev"
Requires-Dist: pre-commit; extra == "dev"
Requires-Dist: recommonmark; extra == "dev"
Requires-Dist: gitverse; extra == "dev"
Dynamic: license-file
